sysnotify/__init__.py
sysnotify-0.1.1.dist-info/licenses/LICENSE
sysnotify-0.1.1.dist-info/METADATA
sysnotify-0.1.1.dist-info/WHEEL
sysnotify-0.1.1.dist-info/top_level.txt
sysnotify-0.1.1.dist-info/RECORD
